{"date": "2024-01-29", "channel_name": "河北卫视", "epg_data": [{"start": "00:33", "end": "01:31", "title": "理想之城(29)"}, {"start": "01:31", "end": "02:25", "title": "理想之城(30)"}, {"start": "02:25", "end": "03:19", "title": "理想之城(31)"}, {"start": "03:19", "end": "04:21", "title": "理想之城(32)"}, {"start": "04:21", "end": "05:23", "title": "父母爱情(34)"}, {"start": "05:23", "end": "06:30", "title": "父母爱情(35)"}, {"start": "06:30", "end": "07:00", "title": "冀时全播报"}, {"start": "07:00", "end": "07:01", "title": "中华人民共和国国歌"}, {"start": "07:01", "end": "07:30", "title": "冀时全播报"}, {"start": "07:30", "end": "08:05", "title": "美丽河北慢直播"}, {"start": "08:05", "end": "08:47", "title": "动画片"}, {"start": "08:47", "end": "09:42", "title": "经典剧场:穆桂英挂帅(31)"}, {"start": "09:42", "end": "11:01", "title": "经典剧场:穆桂英挂帅(32)"}, {"start": "11:01", "end": "11:58", "title": "经典剧场:穆桂英挂帅(33)"}, {"start": "11:58", "end": "13:04", "title": "经典剧场:穆桂英挂帅(34)"}, {"start": "13:04", "end": "14:00", "title": "经典剧场:穆桂英挂帅(35)"}, {"start": "14:00", "end": "14:59", "title": "经典剧场:穆桂英挂帅(36)"}, {"start": "14:59", "end": "16:09", "title": "经典剧场:穆桂英挂帅(37)"}, {"start": "16:09", "end": "17:56", "title": "经典剧场:穆桂英挂帅(38)"}, {"start": "17:56", "end": "18:30", "title": "家政女皇"}, {"start": "18:30", "end": "18:55", "title": "河北新闻联播"}, {"start": "18:55", "end": "19:00", "title": "天气预报"}, {"start": "19:00", "end": "19:33", "title": "转播中央台新闻联播"}, {"start": "19:33", "end": "20:22", "title": "民生剧场:潜行者(35)"}, {"start": "20:22", "end": "21:25", "title": "民生剧场:潜行者(36)"}, {"start": "21:25", "end": "22:10", "title": "中华好家风"}, {"start": "22:10", "end": "23:00", "title": "纪录片"}, {"start": "23:00", "end": "23:30", "title": "你好京津冀"}, {"start": "23:30", "end": "23:59", "title": "纪录片"}]}