{"date": "2024-01-31", "channel_name": "日照新闻综合", "epg_data": [{"start": "06:25", "end": "06:30", "title": "形象片节目预告"}, {"start": "06:30", "end": "07:05", "title": "社会零距离(重播4)"}, {"start": "07:05", "end": "07:30", "title": "日照新闻(重播4)天气预报"}, {"start": "07:30", "end": "07:50", "title": "消费与法魅力日照"}, {"start": "07:50", "end": "11:55", "title": "电视剧"}, {"start": "11:55", "end": "12:30", "title": "社会零距离"}, {"start": "12:30", "end": "13:20", "title": "日照新闻"}, {"start": "13:20", "end": "17:35", "title": "电视剧"}, {"start": "17:35", "end": "17:55", "title": "都市欢乐汇"}, {"start": "17:55", "end": "18:30", "title": "阳光地带"}, {"start": "18:30", "end": "19:00", "title": "转播山东新闻联播"}, {"start": "19:00", "end": "19:38", "title": "转播中央新闻联播"}, {"start": "19:38", "end": "20:05", "title": "日照新闻"}, {"start": "20:05", "end": "20:40", "title": "社会零距离"}, {"start": "20:40", "end": "22:30", "title": "电视剧"}, {"start": "22:30", "end": "22:50", "title": "百姓生活"}, {"start": "22:50", "end": "23:25", "title": "社会零距离"}, {"start": "23:25", "end": "23:50", "title": "日照新闻"}, {"start": "23:50", "end": "23:59", "title": "电视剧"}]}