{"date": "2024-01-30", "channel_name": "爱尔达体育2", "epg_data": [{"start": "02:00", "end": "02:30", "title": "英超名人堂 #33 Eidur Gudjohnsen(普)"}, {"start": "02:30", "end": "03:00", "title": "体坛最前线 1/29(普)"}, {"start": "03:00", "end": "04:30", "title": "HBL 永仁高中 VS 淡水商工 1/28 女子复赛(普)"}, {"start": "04:30", "end": "05:00", "title": "体坛最前线 1/29(普)"}, {"start": "05:00", "end": "06:30", "title": "HBL 金瓯女中 VS 北一女中 1/28 女子复赛(普)"}, {"start": "06:30", "end": "07:00", "title": "体坛最前线 1/29(普)"}, {"start": "07:00", "end": "08:30", "title": "HBL 阳明高中 VS 普门中学 1/28 女子复赛(普)"}, {"start": "08:30", "end": "10:00", "title": "HBL 泰山高中 VS 能仁家商 1/28 男子准决赛(普)"}, {"start": "10:00", "end": "10:30", "title": "体坛最前线 1/29(普)"}, {"start": "10:30", "end": "12:00", "title": "HBL 光复高中 VS 锦和高中 1/28 男子准决赛(普)"}, {"start": "12:00", "end": "13:40", "title": "LIVE HBL 金瓯女中 VS 永平高中 1/30 女子复赛(普)"}, {"start": "13:40", "end": "15:20", "title": "LIVE HBL 阳明高中 VS 永仁高中 1/30 女子复赛(普)"}, {"start": "15:20", "end": "17:00", "title": "LIVE HBL 三重商工 VS 锦和高中 1/30 男子准决赛(普)"}, {"start": "17:00", "end": "18:40", "title": "LIVE HBL 能仁家商 VS 东泰高中 1/30 男子准决赛(普)"}, {"start": "18:40", "end": "21:00", "title": "LIVE HBL 松山高中 VS 光复高中 1/30 男子准决赛(普)"}, {"start": "21:00", "end": "21:30", "title": "NBA动态#12(普)"}, {"start": "21:30", "end": "22:00", "title": "英超名人堂 #33 Eidur Gudjohnsen(普)"}, {"start": "22:00", "end": "22:30", "title": "LIVE 体坛最前线 1/30(普)"}, {"start": "22:30", "end": "22:50", "title": "2024 BWF世界羽球周报 #3 戴资颖 印度站回顾 & 印尼名人赛前瞻(普)"}, {"start": "22:50", "end": "23:50", "title": "欧冠足球志 #16 小组赛回顾(普)"}, {"start": "23:50", "end": "23:59", "title": "LIVE 亚洲杯足球赛 沙乌地 VS 南韩 16强(普)"}, {"start": "02:00", "end": "02:30", "title": "英超名人堂 #33 Eidur Gudjohnsen(普)"}, {"start": "02:30", "end": "03:00", "title": "体坛最前线 1/29(普)"}, {"start": "03:00", "end": "04:30", "title": "HBL 永仁高中 VS 淡水商工 1/28 女子复赛(普)"}, {"start": "04:30", "end": "05:00", "title": "体坛最前线 1/29(普)"}, {"start": "05:00", "end": "06:30", "title": "HBL 金瓯女中 VS 北一女中 1/28 女子复赛(普)"}, {"start": "06:30", "end": "07:00", "title": "体坛最前线 1/29(普)"}, {"start": "07:00", "end": "08:30", "title": "HBL 阳明高中 VS 普门中学 1/28 女子复赛(普)"}, {"start": "08:30", "end": "10:00", "title": "HBL 泰山高中 VS 能仁家商 1/28 男子准决赛(普)"}, {"start": "10:00", "end": "10:30", "title": "体坛最前线 1/29(普)"}, {"start": "10:30", "end": "12:00", "title": "HBL 光复高中 VS 锦和高中 1/28 男子准决赛(普)"}, {"start": "12:00", "end": "13:40", "title": "LIVE HBL 金瓯女中 VS 永平高中 1/30 女子复赛(普)"}, {"start": "13:40", "end": "15:20", "title": "LIVE HBL 阳明高中 VS 永仁高中 1/30 女子复赛(普)"}, {"start": "15:20", "end": "17:00", "title": "LIVE HBL 三重商工 VS 锦和高中 1/30 男子准决赛(普)"}, {"start": "17:00", "end": "18:40", "title": "LIVE HBL 能仁家商 VS 东泰高中 1/30 男子准决赛(普)"}, {"start": "18:40", "end": "21:00", "title": "LIVE HBL 松山高中 VS 光复高中 1/30 男子准决赛(普)"}, {"start": "21:00", "end": "21:30", "title": "NBA动态#12(普)"}, {"start": "21:30", "end": "22:00", "title": "英超名人堂 #33 Eidur Gudjohnsen(普)"}, {"start": "22:00", "end": "22:30", "title": "LIVE 体坛最前线 1/30(普)"}, {"start": "22:30", "end": "22:50", "title": "2024 BWF世界羽球周报 #3 戴资颖 印度站回顾 & 印尼名人赛前瞻(普)"}, {"start": "22:50", "end": "23:50", "title": "欧冠足球志 #16 小组赛回顾(普)"}, {"start": "23:50", "end": "23:59", "title": "LIVE 亚洲杯足球赛 沙乌地 VS 南韩 16强(普)"}, {"start": "02:00", "end": "02:30", "title": "英超名人堂 #33 Eidur Gudjohnsen(普)"}, {"start": "02:30", "end": "03:00", "title": "体坛最前线 1/29(普)"}, {"start": "03:00", "end": "04:30", "title": "HBL 永仁高中 VS 淡水商工 1/28 女子复赛(普)"}, {"start": "04:30", "end": "05:00", "title": "体坛最前线 1/29(普)"}, {"start": "05:00", "end": "06:30", "title": "HBL 金瓯女中 VS 北一女中 1/28 女子复赛(普)"}, {"start": "06:30", "end": "07:00", "title": "体坛最前线 1/29(普)"}, {"start": "07:00", "end": "08:30", "title": "HBL 阳明高中 VS 普门中学 1/28 女子复赛(普)"}, {"start": "08:30", "end": "10:00", "title": "HBL 泰山高中 VS 能仁家商 1/28 男子准决赛(普)"}, {"start": "10:00", "end": "10:30", "title": "体坛最前线 1/29(普)"}, {"start": "10:30", "end": "12:00", "title": "HBL 光复高中 VS 锦和高中 1/28 男子准决赛(普)"}, {"start": "12:00", "end": "13:40", "title": "LIVE HBL 金瓯女中 VS 永平高中 1/30 女子复赛(普)"}, {"start": "13:40", "end": "15:20", "title": "LIVE HBL 阳明高中 VS 永仁高中 1/30 女子复赛(普)"}, {"start": "15:20", "end": "17:00", "title": "LIVE HBL 三重商工 VS 锦和高中 1/30 男子准决赛(普)"}, {"start": "17:00", "end": "18:40", "title": "LIVE HBL 能仁家商 VS 东泰高中 1/30 男子准决赛(普)"}, {"start": "18:40", "end": "21:00", "title": "LIVE HBL 松山高中 VS 光复高中 1/30 男子准决赛(普)"}, {"start": "21:00", "end": "21:30", "title": "NBA动态#12(普)"}, {"start": "21:30", "end": "22:00", "title": "英超名人堂 #33 Eidur Gudjohnsen(普)"}, {"start": "22:00", "end": "22:30", "title": "LIVE 体坛最前线 1/30(普)"}, {"start": "22:30", "end": "22:50", "title": "2024 BWF世界羽球周报 #3 戴资颖 印度站回顾 & 印尼名人赛前瞻(普)"}, {"start": "22:50", "end": "23:50", "title": "欧冠足球志 #16 小组赛回顾(普)"}, {"start": "23:50", "end": "23:59", "title": "LIVE 亚洲杯足球赛 沙乌地 VS 南韩 16强(普)"}, {"start": "02:00", "end": "02:30", "title": "英超名人堂 #33 Eidur Gudjohnsen(普)"}, {"start": "02:30", "end": "03:00", "title": "体坛最前线 1/29(普)"}, {"start": "03:00", "end": "04:30", "title": "HBL 永仁高中 VS 淡水商工 1/28 女子复赛(普)"}, {"start": "04:30", "end": "05:00", "title": "体坛最前线 1/29(普)"}, {"start": "05:00", "end": "06:30", "title": "HBL 金瓯女中 VS 北一女中 1/28 女子复赛(普)"}, {"start": "06:30", "end": "07:00", "title": "体坛最前线 1/29(普)"}, {"start": "07:00", "end": "08:30", "title": "HBL 阳明高中 VS 普门中学 1/28 女子复赛(普)"}, {"start": "08:30", "end": "10:00", "title": "HBL 泰山高中 VS 能仁家商 1/28 男子准决赛(普)"}, {"start": "10:00", "end": "10:30", "title": "体坛最前线 1/29(普)"}, {"start": "10:30", "end": "12:00", "title": "HBL 光复高中 VS 锦和高中 1/28 男子准决赛(普)"}, {"start": "12:00", "end": "13:40", "title": "LIVE HBL 金瓯女中 VS 永平高中 1/30 女子复赛(普)"}, {"start": "13:40", "end": "15:20", "title": "LIVE HBL 阳明高中 VS 永仁高中 1/30 女子复赛(普)"}, {"start": "15:20", "end": "17:00", "title": "LIVE HBL 三重商工 VS 锦和高中 1/30 男子准决赛(普)"}, {"start": "17:00", "end": "18:40", "title": "LIVE HBL 能仁家商 VS 东泰高中 1/30 男子准决赛(普)"}, {"start": "18:40", "end": "21:00", "title": "LIVE HBL 松山高中 VS 光复高中 1/30 男子准决赛(普)"}, {"start": "21:00", "end": "21:30", "title": "NBA动态#12(普)"}, {"start": "21:30", "end": "22:00", "title": "英超名人堂 #33 Eidur Gudjohnsen(普)"}, {"start": "22:00", "end": "22:30", "title": "LIVE 体坛最前线 1/30(普)"}, {"start": "22:30", "end": "22:50", "title": "2024 BWF世界羽球周报 #3 戴资颖 印度站回顾 & 印尼名人赛前瞻(普)"}, {"start": "22:50", "end": "23:50", "title": "欧冠足球志 #16 小组赛回顾(普)"}, {"start": "23:50", "end": "23:59", "title": "LIVE 亚洲杯足球赛 沙乌地 VS 南韩 16强(普)"}, {"start": "02:00", "end": "02:30", "title": "英超名人堂 #33 Eidur Gudjohnsen(普)"}, {"start": "02:30", "end": "03:00", "title": "体坛最前线 1/29(普)"}, {"start": "03:00", "end": "04:30", "title": "HBL 永仁高中 VS 淡水商工 1/28 女子复赛(普)"}, {"start": "04:30", "end": "05:00", "title": "体坛最前线 1/29(普)"}, {"start": "05:00", "end": "06:30", "title": "HBL 金瓯女中 VS 北一女中 1/28 女子复赛(普)"}, {"start": "06:30", "end": "07:00", "title": "体坛最前线 1/29(普)"}, {"start": "07:00", "end": "08:30", "title": "HBL 阳明高中 VS 普门中学 1/28 女子复赛(普)"}, {"start": "08:30", "end": "10:00", "title": "HBL 泰山高中 VS 能仁家商 1/28 男子准决赛(普)"}, {"start": "10:00", "end": "10:30", "title": "体坛最前线 1/29(普)"}, {"start": "10:30", "end": "12:00", "title": "HBL 光复高中 VS 锦和高中 1/28 男子准决赛(普)"}, {"start": "12:00", "end": "13:40", "title": "LIVE HBL 金瓯女中 VS 永平高中 1/30 女子复赛(普)"}, {"start": "13:40", "end": "15:20", "title": "LIVE HBL 阳明高中 VS 永仁高中 1/30 女子复赛(普)"}, {"start": "15:20", "end": "17:00", "title": "LIVE HBL 三重商工 VS 锦和高中 1/30 男子准决赛(普)"}, {"start": "17:00", "end": "18:40", "title": "LIVE HBL 能仁家商 VS 东泰高中 1/30 男子准决赛(普)"}, {"start": "18:40", "end": "21:00", "title": "LIVE HBL 松山高中 VS 光复高中 1/30 男子准决赛(普)"}, {"start": "21:00", "end": "21:30", "title": "NBA动态#12(普)"}, {"start": "21:30", "end": "22:00", "title": "英超名人堂 #33 Eidur Gudjohnsen(普)"}, {"start": "22:00", "end": "22:30", "title": "LIVE 体坛最前线 1/30(普)"}, {"start": "22:30", "end": "22:50", "title": "2024 BWF世界羽球周报 #3 戴资颖 印度站回顾 & 印尼名人赛前瞻(普)"}, {"start": "22:50", "end": "23:50", "title": "欧冠足球志 #16 小组赛回顾(普)"}, {"start": "23:50", "end": "23:59", "title": "LIVE 亚洲杯足球赛 沙乌地 VS 南韩 16强(普)"}, {"start": "02:00", "end": "02:30", "title": "英超名人堂 #33 Eidur Gudjohnsen(普)"}, {"start": "02:30", "end": "03:00", "title": "体坛最前线 1/29(普)"}, {"start": "03:00", "end": "04:30", "title": "HBL 永仁高中 VS 淡水商工 1/28 女子复赛(普)"}, {"start": "04:30", "end": "05:00", "title": "体坛最前线 1/29(普)"}, {"start": "05:00", "end": "06:30", "title": "HBL 金瓯女中 VS 北一女中 1/28 女子复赛(普)"}, {"start": "06:30", "end": "07:00", "title": "体坛最前线 1/29(普)"}, {"start": "07:00", "end": "08:30", "title": "HBL 阳明高中 VS 普门中学 1/28 女子复赛(普)"}, {"start": "08:30", "end": "10:00", "title": "HBL 泰山高中 VS 能仁家商 1/28 男子准决赛(普)"}, {"start": "10:00", "end": "10:30", "title": "体坛最前线 1/29(普)"}, {"start": "10:30", "end": "12:00", "title": "HBL 光复高中 VS 锦和高中 1/28 男子准决赛(普)"}, {"start": "12:00", "end": "13:40", "title": "LIVE HBL 金瓯女中 VS 永平高中 1/30 女子复赛(普)"}, {"start": "13:40", "end": "15:20", "title": "LIVE HBL 阳明高中 VS 永仁高中 1/30 女子复赛(普)"}, {"start": "15:20", "end": "17:00", "title": "LIVE HBL 三重商工 VS 锦和高中 1/30 男子准决赛(普)"}, {"start": "17:00", "end": "18:40", "title": "LIVE HBL 能仁家商 VS 东泰高中 1/30 男子准决赛(普)"}, {"start": "18:40", "end": "21:00", "title": "LIVE HBL 松山高中 VS 光复高中 1/30 男子准决赛(普)"}, {"start": "21:00", "end": "21:30", "title": "NBA动态#12(普)"}, {"start": "21:30", "end": "22:00", "title": "英超名人堂 #33 Eidur Gudjohnsen(普)"}, {"start": "22:00", "end": "22:30", "title": "LIVE 体坛最前线 1/30(普)"}, {"start": "22:30", "end": "22:50", "title": "2024 BWF世界羽球周报 #3 戴资颖 印度站回顾 & 印尼名人赛前瞻(普)"}, {"start": "22:50", "end": "23:50", "title": "欧冠足球志 #16 小组赛回顾(普)"}, {"start": "23:50", "end": "23:59", "title": "LIVE 亚洲杯足球赛 沙乌地 VS 南韩 16强(普)"}, {"start": "02:00", "end": "02:30", "title": "英超名人堂 #33 Eidur Gudjohnsen(普)"}, {"start": "02:30", "end": "03:00", "title": "体坛最前线 1/29(普)"}, {"start": "03:00", "end": "04:30", "title": "HBL 永仁高中 VS 淡水商工 1/28 女子复赛(普)"}, {"start": "04:30", "end": "05:00", "title": "体坛最前线 1/29(普)"}, {"start": "05:00", "end": "06:30", "title": "HBL 金瓯女中 VS 北一女中 1/28 女子复赛(普)"}, {"start": "06:30", "end": "07:00", "title": "体坛最前线 1/29(普)"}, {"start": "07:00", "end": "08:30", "title": "HBL 阳明高中 VS 普门中学 1/28 女子复赛(普)"}, {"start": "08:30", "end": "10:00", "title": "HBL 泰山高中 VS 能仁家商 1/28 男子准决赛(普)"}, {"start": "10:00", "end": "10:30", "title": "体坛最前线 1/29(普)"}, {"start": "10:30", "end": "12:00", "title": "HBL 光复高中 VS 锦和高中 1/28 男子准决赛(普)"}, {"start": "12:00", "end": "13:40", "title": "LIVE HBL 金瓯女中 VS 永平高中 1/30 女子复赛(普)"}, {"start": "13:40", "end": "15:20", "title": "LIVE HBL 阳明高中 VS 永仁高中 1/30 女子复赛(普)"}, {"start": "15:20", "end": "17:00", "title": "LIVE HBL 三重商工 VS 锦和高中 1/30 男子准决赛(普)"}, {"start": "17:00", "end": "18:40", "title": "LIVE HBL 能仁家商 VS 东泰高中 1/30 男子准决赛(普)"}, {"start": "18:40", "end": "21:00", "title": "LIVE HBL 松山高中 VS 光复高中 1/30 男子准决赛(普)"}, {"start": "21:00", "end": "21:30", "title": "NBA动态#12(普)"}, {"start": "21:30", "end": "22:00", "title": "英超名人堂 #33 Eidur Gudjohnsen(普)"}, {"start": "22:00", "end": "22:30", "title": "LIVE 体坛最前线 1/30(普)"}, {"start": "22:30", "end": "22:50", "title": "2024 BWF世界羽球周报 #3 戴资颖 印度站回顾 & 印尼名人赛前瞻(普)"}, {"start": "22:50", "end": "23:50", "title": "欧冠足球志 #16 小组赛回顾(普)"}, {"start": "23:50", "end": "23:59", "title": "LIVE 亚洲杯足球赛 沙乌地 VS 南韩 16强(普)"}, {"start": "02:00", "end": "02:30", "title": "英超名人堂 #33 Eidur Gudjohnsen(普)"}, {"start": "02:30", "end": "03:00", "title": "体坛最前线 1/29(普)"}, {"start": "03:00", "end": "04:30", "title": "HBL 永仁高中 VS 淡水商工 1/28 女子复赛(普)"}, {"start": "04:30", "end": "05:00", "title": "体坛最前线 1/29(普)"}, {"start": "05:00", "end": "06:30", "title": "HBL 金瓯女中 VS 北一女中 1/28 女子复赛(普)"}, {"start": "06:30", "end": "07:00", "title": "体坛最前线 1/29(普)"}, {"start": "07:00", "end": "08:30", "title": "HBL 阳明高中 VS 普门中学 1/28 女子复赛(普)"}, {"start": "08:30", "end": "10:00", "title": "HBL 泰山高中 VS 能仁家商 1/28 男子准决赛(普)"}, {"start": "10:00", "end": "10:30", "title": "体坛最前线 1/29(普)"}, {"start": "10:30", "end": "12:00", "title": "HBL 光复高中 VS 锦和高中 1/28 男子准决赛(普)"}, {"start": "12:00", "end": "13:40", "title": "LIVE HBL 金瓯女中 VS 永平高中 1/30 女子复赛(普)"}, {"start": "13:40", "end": "15:20", "title": "LIVE HBL 阳明高中 VS 永仁高中 1/30 女子复赛(普)"}, {"start": "15:20", "end": "17:00", "title": "LIVE HBL 三重商工 VS 锦和高中 1/30 男子准决赛(普)"}, {"start": "17:00", "end": "18:40", "title": "LIVE HBL 能仁家商 VS 东泰高中 1/30 男子准决赛(普)"}, {"start": "18:40", "end": "21:00", "title": "LIVE HBL 松山高中 VS 光复高中 1/30 男子准决赛(普)"}, {"start": "21:00", "end": "21:30", "title": "NBA动态#12(普)"}, {"start": "21:30", "end": "22:00", "title": "英超名人堂 #33 Eidur Gudjohnsen(普)"}, {"start": "22:00", "end": "22:30", "title": "LIVE 体坛最前线 1/30(普)"}, {"start": "22:30", "end": "22:50", "title": "2024 BWF世界羽球周报 #3 戴资颖 印度站回顾 & 印尼名人赛前瞻(普)"}, {"start": "22:50", "end": "23:50", "title": "欧冠足球志 #16 小组赛回顾(普)"}, {"start": "23:50", "end": "23:59", "title": "LIVE 亚洲杯足球赛 沙乌地 VS 南韩 16强(普)"}, {"start": "02:00", "end": "02:30", "title": "英超名人堂 #33 Eidur Gudjohnsen(普)"}, {"start": "02:30", "end": "03:00", "title": "体坛最前线 1/29(普)"}, {"start": "03:00", "end": "04:30", "title": "HBL 永仁高中 VS 淡水商工 1/28 女子复赛(普)"}, {"start": "04:30", "end": "05:00", "title": "体坛最前线 1/29(普)"}, {"start": "05:00", "end": "06:30", "title": "HBL 金瓯女中 VS 北一女中 1/28 女子复赛(普)"}, {"start": "06:30", "end": "07:00", "title": "体坛最前线 1/29(普)"}, {"start": "07:00", "end": "08:30", "title": "HBL 阳明高中 VS 普门中学 1/28 女子复赛(普)"}, {"start": "08:30", "end": "10:00", "title": "HBL 泰山高中 VS 能仁家商 1/28 男子准决赛(普)"}, {"start": "10:00", "end": "10:30", "title": "体坛最前线 1/29(普)"}, {"start": "10:30", "end": "12:00", "title": "HBL 光复高中 VS 锦和高中 1/28 男子准决赛(普)"}, {"start": "12:00", "end": "13:40", "title": "LIVE HBL 金瓯女中 VS 永平高中 1/30 女子复赛(普)"}, {"start": "13:40", "end": "15:20", "title": "LIVE HBL 阳明高中 VS 永仁高中 1/30 女子复赛(普)"}, {"start": "15:20", "end": "17:00", "title": "LIVE HBL 三重商工 VS 锦和高中 1/30 男子准决赛(普)"}, {"start": "17:00", "end": "18:40", "title": "LIVE HBL 能仁家商 VS 东泰高中 1/30 男子准决赛(普)"}, {"start": "18:40", "end": "21:00", "title": "LIVE HBL 松山高中 VS 光复高中 1/30 男子准决赛(普)"}, {"start": "21:00", "end": "21:30", "title": "NBA动态#12(普)"}, {"start": "21:30", "end": "22:00", "title": "英超名人堂 #33 Eidur Gudjohnsen(普)"}, {"start": "22:00", "end": "22:30", "title": "LIVE 体坛最前线 1/30(普)"}, {"start": "22:30", "end": "22:50", "title": "2024 BWF世界羽球周报 #3 戴资颖 印度站回顾 & 印尼名人赛前瞻(普)"}, {"start": "22:50", "end": "23:50", "title": "欧冠足球志 #16 小组赛回顾(普)"}, {"start": "23:50", "end": "23:59", "title": "LIVE 亚洲杯足球赛 沙乌地 VS 南韩 16强(普)"}, {"start": "02:00", "end": "02:30", "title": "英超名人堂 #33 Eidur Gudjohnsen(普)"}, {"start": "02:30", "end": "03:00", "title": "体坛最前线 1/29(普)"}, {"start": "03:00", "end": "04:30", "title": "HBL 永仁高中 VS 淡水商工 1/28 女子复赛(普)"}, {"start": "04:30", "end": "05:00", "title": "体坛最前线 1/29(普)"}, {"start": "05:00", "end": "06:30", "title": "HBL 金瓯女中 VS 北一女中 1/28 女子复赛(普)"}, {"start": "06:30", "end": "07:00", "title": "体坛最前线 1/29(普)"}, {"start": "07:00", "end": "08:30", "title": "HBL 阳明高中 VS 普门中学 1/28 女子复赛(普)"}, {"start": "08:30", "end": "10:00", "title": "HBL 泰山高中 VS 能仁家商 1/28 男子准决赛(普)"}, {"start": "10:00", "end": "10:30", "title": "体坛最前线 1/29(普)"}, {"start": "10:30", "end": "12:00", "title": "HBL 光复高中 VS 锦和高中 1/28 男子准决赛(普)"}, {"start": "12:00", "end": "13:40", "title": "LIVE HBL 金瓯女中 VS 永平高中 1/30 女子复赛(普)"}, {"start": "13:40", "end": "15:20", "title": "LIVE HBL 阳明高中 VS 永仁高中 1/30 女子复赛(普)"}, {"start": "15:20", "end": "17:00", "title": "LIVE HBL 三重商工 VS 锦和高中 1/30 男子准决赛(普)"}, {"start": "17:00", "end": "18:40", "title": "LIVE HBL 能仁家商 VS 东泰高中 1/30 男子准决赛(普)"}, {"start": "18:40", "end": "21:00", "title": "LIVE HBL 松山高中 VS 光复高中 1/30 男子准决赛(普)"}, {"start": "21:00", "end": "21:30", "title": "NBA动态#12(普)"}, {"start": "21:30", "end": "22:00", "title": "英超名人堂 #33 Eidur Gudjohnsen(普)"}, {"start": "22:00", "end": "22:30", "title": "LIVE 体坛最前线 1/30(普)"}, {"start": "22:30", "end": "22:50", "title": "2024 BWF世界羽球周报 #3 戴资颖 印度站回顾 & 印尼名人赛前瞻(普)"}, {"start": "22:50", "end": "23:50", "title": "欧冠足球志 #16 小组赛回顾(普)"}, {"start": "23:50", "end": "23:59", "title": "LIVE 亚洲杯足球赛 沙乌地 VS 南韩 16强(普)"}, {"start": "02:00", "end": "02:30", "title": "英超名人堂 #33 Eidur Gudjohnsen(普)"}, {"start": "02:30", "end": "03:00", "title": "体坛最前线 1/29(普)"}, {"start": "03:00", "end": "04:30", "title": "HBL 永仁高中 VS 淡水商工 1/28 女子复赛(普)"}, {"start": "04:30", "end": "05:00", "title": "体坛最前线 1/29(普)"}, {"start": "05:00", "end": "06:30", "title": "HBL 金瓯女中 VS 北一女中 1/28 女子复赛(普)"}, {"start": "06:30", "end": "07:00", "title": "体坛最前线 1/29(普)"}, {"start": "07:00", "end": "08:30", "title": "HBL 阳明高中 VS 普门中学 1/28 女子复赛(普)"}, {"start": "08:30", "end": "10:00", "title": "HBL 泰山高中 VS 能仁家商 1/28 男子准决赛(普)"}, {"start": "10:00", "end": "10:30", "title": "体坛最前线 1/29(普)"}, {"start": "10:30", "end": "12:00", "title": "HBL 光复高中 VS 锦和高中 1/28 男子准决赛(普)"}, {"start": "12:00", "end": "13:40", "title": "LIVE HBL 金瓯女中 VS 永平高中 1/30 女子复赛(普)"}, {"start": "13:40", "end": "15:20", "title": "LIVE HBL 阳明高中 VS 永仁高中 1/30 女子复赛(普)"}, {"start": "15:20", "end": "17:00", "title": "LIVE HBL 三重商工 VS 锦和高中 1/30 男子准决赛(普)"}, {"start": "17:00", "end": "18:40", "title": "LIVE HBL 能仁家商 VS 东泰高中 1/30 男子准决赛(普)"}, {"start": "18:40", "end": "21:00", "title": "LIVE HBL 松山高中 VS 光复高中 1/30 男子准决赛(普)"}, {"start": "21:00", "end": "21:30", "title": "NBA动态#12(普)"}, {"start": "21:30", "end": "22:00", "title": "英超名人堂 #33 Eidur Gudjohnsen(普)"}, {"start": "22:00", "end": "22:30", "title": "LIVE 体坛最前线 1/30(普)"}, {"start": "22:30", "end": "22:50", "title": "2024 BWF世界羽球周报 #3 戴资颖 印度站回顾 & 印尼名人赛前瞻(普)"}, {"start": "22:50", "end": "23:50", "title": "欧冠足球志 #16 小组赛回顾(普)"}, {"start": "23:50", "end": "23:59", "title": "LIVE 亚洲杯足球赛 沙乌地 VS 南韩 16强(普)"}, {"start": "02:00", "end": "02:30", "title": "英超名人堂 #33 Eidur Gudjohnsen(普)"}, {"start": "02:30", "end": "03:00", "title": "体坛最前线 1/29(普)"}, {"start": "03:00", "end": "04:30", "title": "HBL 永仁高中 VS 淡水商工 1/28 女子复赛(普)"}, {"start": "04:30", "end": "05:00", "title": "体坛最前线 1/29(普)"}, {"start": "05:00", "end": "06:30", "title": "HBL 金瓯女中 VS 北一女中 1/28 女子复赛(普)"}, {"start": "06:30", "end": "07:00", "title": "体坛最前线 1/29(普)"}, {"start": "07:00", "end": "08:30", "title": "HBL 阳明高中 VS 普门中学 1/28 女子复赛(普)"}, {"start": "08:30", "end": "10:00", "title": "HBL 泰山高中 VS 能仁家商 1/28 男子准决赛(普)"}, {"start": "10:00", "end": "10:30", "title": "体坛最前线 1/29(普)"}, {"start": "10:30", "end": "12:00", "title": "HBL 光复高中 VS 锦和高中 1/28 男子准决赛(普)"}, {"start": "12:00", "end": "13:40", "title": "LIVE HBL 金瓯女中 VS 永平高中 1/30 女子复赛(普)"}, {"start": "13:40", "end": "15:20", "title": "LIVE HBL 阳明高中 VS 永仁高中 1/30 女子复赛(普)"}, {"start": "15:20", "end": "17:00", "title": "LIVE HBL 三重商工 VS 锦和高中 1/30 男子准决赛(普)"}, {"start": "17:00", "end": "18:40", "title": "LIVE HBL 能仁家商 VS 东泰高中 1/30 男子准决赛(普)"}, {"start": "18:40", "end": "21:00", "title": "LIVE HBL 松山高中 VS 光复高中 1/30 男子准决赛(普)"}, {"start": "21:00", "end": "21:30", "title": "NBA动态#12(普)"}, {"start": "21:30", "end": "22:00", "title": "英超名人堂 #33 Eidur Gudjohnsen(普)"}, {"start": "22:00", "end": "22:30", "title": "LIVE 体坛最前线 1/30(普)"}, {"start": "22:30", "end": "22:50", "title": "2024 BWF世界羽球周报 #3 戴资颖 印度站回顾 & 印尼名人赛前瞻(普)"}, {"start": "22:50", "end": "23:50", "title": "欧冠足球志 #16 小组赛回顾(普)"}, {"start": "23:50", "end": "23:59", "title": "LIVE 亚洲杯足球赛 沙乌地 VS 南韩 16强(普)"}, {"start": "02:00", "end": "02:30", "title": "英超名人堂 #33 Eidur Gudjohnsen(普)"}, {"start": "02:30", "end": "03:00", "title": "体坛最前线 1/29(普)"}, {"start": "03:00", "end": "04:30", "title": "HBL 永仁高中 VS 淡水商工 1/28 女子复赛(普)"}, {"start": "04:30", "end": "05:00", "title": "体坛最前线 1/29(普)"}, {"start": "05:00", "end": "06:30", "title": "HBL 金瓯女中 VS 北一女中 1/28 女子复赛(普)"}, {"start": "06:30", "end": "07:00", "title": "体坛最前线 1/29(普)"}, {"start": "07:00", "end": "08:30", "title": "HBL 阳明高中 VS 普门中学 1/28 女子复赛(普)"}, {"start": "08:30", "end": "10:00", "title": "HBL 泰山高中 VS 能仁家商 1/28 男子准决赛(普)"}, {"start": "10:00", "end": "10:30", "title": "体坛最前线 1/29(普)"}, {"start": "10:30", "end": "12:00", "title": "HBL 光复高中 VS 锦和高中 1/28 男子准决赛(普)"}, {"start": "12:00", "end": "13:40", "title": "LIVE HBL 金瓯女中 VS 永平高中 1/30 女子复赛(普)"}, {"start": "13:40", "end": "15:20", "title": "LIVE HBL 阳明高中 VS 永仁高中 1/30 女子复赛(普)"}, {"start": "15:20", "end": "17:00", "title": "LIVE HBL 三重商工 VS 锦和高中 1/30 男子准决赛(普)"}, {"start": "17:00", "end": "18:40", "title": "LIVE HBL 能仁家商 VS 东泰高中 1/30 男子准决赛(普)"}, {"start": "18:40", "end": "21:00", "title": "LIVE HBL 松山高中 VS 光复高中 1/30 男子准决赛(普)"}, {"start": "21:00", "end": "21:30", "title": "NBA动态#12(普)"}, {"start": "21:30", "end": "22:00", "title": "英超名人堂 #33 Eidur Gudjohnsen(普)"}, {"start": "22:00", "end": "22:30", "title": "LIVE 体坛最前线 1/30(普)"}, {"start": "22:30", "end": "22:50", "title": "2024 BWF世界羽球周报 #3 戴资颖 印度站回顾 & 印尼名人赛前瞻(普)"}, {"start": "22:50", "end": "23:50", "title": "欧冠足球志 #16 小组赛回顾(普)"}, {"start": "23:50", "end": "23:59", "title": "LIVE 亚洲杯足球赛 沙乌地 VS 南韩 16强(普)"}, {"start": "02:00", "end": "02:30", "title": "英超名人堂 #33 Eidur Gudjohnsen(普)"}, {"start": "02:30", "end": "03:00", "title": "体坛最前线 1/29(普)"}, {"start": "03:00", "end": "04:30", "title": "HBL 永仁高中 VS 淡水商工 1/28 女子复赛(普)"}, {"start": "04:30", "end": "05:00", "title": "体坛最前线 1/29(普)"}, {"start": "05:00", "end": "06:30", "title": "HBL 金瓯女中 VS 北一女中 1/28 女子复赛(普)"}, {"start": "06:30", "end": "07:00", "title": "体坛最前线 1/29(普)"}, {"start": "07:00", "end": "08:30", "title": "HBL 阳明高中 VS 普门中学 1/28 女子复赛(普)"}, {"start": "08:30", "end": "10:00", "title": "HBL 泰山高中 VS 能仁家商 1/28 男子准决赛(普)"}, {"start": "10:00", "end": "10:30", "title": "体坛最前线 1/29(普)"}, {"start": "10:30", "end": "12:00", "title": "HBL 光复高中 VS 锦和高中 1/28 男子准决赛(普)"}, {"start": "12:00", "end": "13:40", "title": "LIVE HBL 金瓯女中 VS 永平高中 1/30 女子复赛(普)"}, {"start": "13:40", "end": "15:20", "title": "LIVE HBL 阳明高中 VS 永仁高中 1/30 女子复赛(普)"}, {"start": "15:20", "end": "17:00", "title": "LIVE HBL 三重商工 VS 锦和高中 1/30 男子准决赛(普)"}, {"start": "17:00", "end": "18:40", "title": "LIVE HBL 能仁家商 VS 东泰高中 1/30 男子准决赛(普)"}, {"start": "18:40", "end": "21:00", "title": "LIVE HBL 松山高中 VS 光复高中 1/30 男子准决赛(普)"}, {"start": "21:00", "end": "21:30", "title": "NBA动态#12(普)"}, {"start": "21:30", "end": "22:00", "title": "英超名人堂 #33 Eidur Gudjohnsen(普)"}, {"start": "22:00", "end": "22:30", "title": "LIVE 体坛最前线 1/30(普)"}, {"start": "22:30", "end": "22:50", "title": "2024 BWF世界羽球周报 #3 戴资颖 印度站回顾 & 印尼名人赛前瞻(普)"}, {"start": "22:50", "end": "23:50", "title": "欧冠足球志 #16 小组赛回顾(普)"}, {"start": "23:50", "end": "23:59", "title": "LIVE 亚洲杯足球赛 沙乌地 VS 南韩 16强(普)"}, {"start": "02:00", "end": "02:30", "title": "英超名人堂 #33 Eidur Gudjohnsen(普)"}, {"start": "02:30", "end": "03:00", "title": "体坛最前线 1/29(普)"}, {"start": "03:00", "end": "04:30", "title": "HBL 永仁高中 VS 淡水商工 1/28 女子复赛(普)"}, {"start": "04:30", "end": "05:00", "title": "体坛最前线 1/29(普)"}, {"start": "05:00", "end": "06:30", "title": "HBL 金瓯女中 VS 北一女中 1/28 女子复赛(普)"}, {"start": "06:30", "end": "07:00", "title": "体坛最前线 1/29(普)"}, {"start": "07:00", "end": "08:30", "title": "HBL 阳明高中 VS 普门中学 1/28 女子复赛(普)"}, {"start": "08:30", "end": "10:00", "title": "HBL 泰山高中 VS 能仁家商 1/28 男子准决赛(普)"}, {"start": "10:00", "end": "10:30", "title": "体坛最前线 1/29(普)"}, {"start": "10:30", "end": "12:00", "title": "HBL 光复高中 VS 锦和高中 1/28 男子准决赛(普)"}, {"start": "12:00", "end": "13:40", "title": "LIVE HBL 金瓯女中 VS 永平高中 1/30 女子复赛(普)"}, {"start": "13:40", "end": "15:20", "title": "LIVE HBL 阳明高中 VS 永仁高中 1/30 女子复赛(普)"}, {"start": "15:20", "end": "17:00", "title": "LIVE HBL 三重商工 VS 锦和高中 1/30 男子准决赛(普)"}, {"start": "17:00", "end": "18:40", "title": "LIVE HBL 能仁家商 VS 东泰高中 1/30 男子准决赛(普)"}, {"start": "18:40", "end": "21:00", "title": "LIVE HBL 松山高中 VS 光复高中 1/30 男子准决赛(普)"}, {"start": "21:00", "end": "21:30", "title": "NBA动态#12(普)"}, {"start": "21:30", "end": "22:00", "title": "英超名人堂 #33 Eidur Gudjohnsen(普)"}, {"start": "22:00", "end": "22:30", "title": "LIVE 体坛最前线 1/30(普)"}, {"start": "22:30", "end": "22:50", "title": "2024 BWF世界羽球周报 #3 戴资颖 印度站回顾 & 印尼名人赛前瞻(普)"}, {"start": "22:50", "end": "23:50", "title": "欧冠足球志 #16 小组赛回顾(普)"}, {"start": "23:50", "end": "23:59", "title": "LIVE 亚洲杯足球赛 沙乌地 VS 南韩 16强(普)"}, {"start": "02:00", "end": "02:30", "title": "英超名人堂 #33 Eidur Gudjohnsen(普)"}, {"start": "02:30", "end": "03:00", "title": "体坛最前线 1/29(普)"}, {"start": "03:00", "end": "04:30", "title": "HBL 永仁高中 VS 淡水商工 1/28 女子复赛(普)"}, {"start": "04:30", "end": "05:00", "title": "体坛最前线 1/29(普)"}, {"start": "05:00", "end": "06:30", "title": "HBL 金瓯女中 VS 北一女中 1/28 女子复赛(普)"}, {"start": "06:30", "end": "07:00", "title": "体坛最前线 1/29(普)"}, {"start": "07:00", "end": "08:30", "title": "HBL 阳明高中 VS 普门中学 1/28 女子复赛(普)"}, {"start": "08:30", "end": "10:00", "title": "HBL 泰山高中 VS 能仁家商 1/28 男子准决赛(普)"}, {"start": "10:00", "end": "10:30", "title": "体坛最前线 1/29(普)"}, {"start": "10:30", "end": "12:00", "title": "HBL 光复高中 VS 锦和高中 1/28 男子准决赛(普)"}, {"start": "12:00", "end": "13:40", "title": "LIVE HBL 金瓯女中 VS 永平高中 1/30 女子复赛(普)"}, {"start": "13:40", "end": "15:20", "title": "LIVE HBL 阳明高中 VS 永仁高中 1/30 女子复赛(普)"}, {"start": "15:20", "end": "17:00", "title": "LIVE HBL 三重商工 VS 锦和高中 1/30 男子准决赛(普)"}, {"start": "17:00", "end": "18:40", "title": "LIVE HBL 能仁家商 VS 东泰高中 1/30 男子准决赛(普)"}, {"start": "18:40", "end": "21:00", "title": "LIVE HBL 松山高中 VS 光复高中 1/30 男子准决赛(普)"}, {"start": "21:00", "end": "21:30", "title": "NBA动态#12(普)"}, {"start": "21:30", "end": "22:00", "title": "英超名人堂 #33 Eidur Gudjohnsen(普)"}, {"start": "22:00", "end": "22:30", "title": "LIVE 体坛最前线 1/30(普)"}, {"start": "22:30", "end": "22:50", "title": "2024 BWF世界羽球周报 #3 戴资颖 印度站回顾 & 印尼名人赛前瞻(普)"}, {"start": "22:50", "end": "23:50", "title": "欧冠足球志 #16 小组赛回顾(普)"}, {"start": "23:50", "end": "23:59", "title": "LIVE 亚洲杯足球赛 沙乌地 VS 南韩 16强(普)"}, {"start": "02:00", "end": "02:30", "title": "英超名人堂 #33 Eidur Gudjohnsen(普)"}, {"start": "02:30", "end": "03:00", "title": "体坛最前线 1/29(普)"}, {"start": "03:00", "end": "04:30", "title": "HBL 永仁高中 VS 淡水商工 1/28 女子复赛(普)"}, {"start": "04:30", "end": "05:00", "title": "体坛最前线 1/29(普)"}, {"start": "05:00", "end": "06:30", "title": "HBL 金瓯女中 VS 北一女中 1/28 女子复赛(普)"}, {"start": "06:30", "end": "07:00", "title": "体坛最前线 1/29(普)"}, {"start": "07:00", "end": "08:30", "title": "HBL 阳明高中 VS 普门中学 1/28 女子复赛(普)"}, {"start": "08:30", "end": "10:00", "title": "HBL 泰山高中 VS 能仁家商 1/28 男子准决赛(普)"}, {"start": "10:00", "end": "10:30", "title": "体坛最前线 1/29(普)"}, {"start": "10:30", "end": "12:00", "title": "HBL 光复高中 VS 锦和高中 1/28 男子准决赛(普)"}, {"start": "12:00", "end": "13:40", "title": "LIVE HBL 金瓯女中 VS 永平高中 1/30 女子复赛(普)"}, {"start": "13:40", "end": "15:20", "title": "LIVE HBL 阳明高中 VS 永仁高中 1/30 女子复赛(普)"}, {"start": "15:20", "end": "17:00", "title": "LIVE HBL 三重商工 VS 锦和高中 1/30 男子准决赛(普)"}, {"start": "17:00", "end": "18:40", "title": "LIVE HBL 能仁家商 VS 东泰高中 1/30 男子准决赛(普)"}, {"start": "18:40", "end": "21:00", "title": "LIVE HBL 松山高中 VS 光复高中 1/30 男子准决赛(普)"}, {"start": "21:00", "end": "21:30", "title": "NBA动态#12(普)"}, {"start": "21:30", "end": "22:00", "title": "英超名人堂 #33 Eidur Gudjohnsen(普)"}, {"start": "22:00", "end": "22:30", "title": "LIVE 体坛最前线 1/30(普)"}, {"start": "22:30", "end": "22:50", "title": "2024 BWF世界羽球周报 #3 戴资颖 印度站回顾 & 印尼名人赛前瞻(普)"}, {"start": "22:50", "end": "23:50", "title": "欧冠足球志 #16 小组赛回顾(普)"}, {"start": "23:50", "end": "23:59", "title": "LIVE 亚洲杯足球赛 沙乌地 VS 南韩 16强(普)"}, {"start": "02:00", "end": "02:30", "title": "英超名人堂 #33 Eidur Gudjohnsen(普)"}, {"start": "02:30", "end": "03:00", "title": "体坛最前线 1/29(普)"}, {"start": "03:00", "end": "04:30", "title": "HBL 永仁高中 VS 淡水商工 1/28 女子复赛(普)"}, {"start": "04:30", "end": "05:00", "title": "体坛最前线 1/29(普)"}, {"start": "05:00", "end": "06:30", "title": "HBL 金瓯女中 VS 北一女中 1/28 女子复赛(普)"}, {"start": "06:30", "end": "07:00", "title": "体坛最前线 1/29(普)"}, {"start": "07:00", "end": "08:30", "title": "HBL 阳明高中 VS 普门中学 1/28 女子复赛(普)"}, {"start": "08:30", "end": "10:00", "title": "HBL 泰山高中 VS 能仁家商 1/28 男子准决赛(普)"}, {"start": "10:00", "end": "10:30", "title": "体坛最前线 1/29(普)"}, {"start": "10:30", "end": "12:00", "title": "HBL 光复高中 VS 锦和高中 1/28 男子准决赛(普)"}, {"start": "12:00", "end": "13:40", "title": "LIVE HBL 金瓯女中 VS 永平高中 1/30 女子复赛(普)"}, {"start": "13:40", "end": "15:20", "title": "LIVE HBL 阳明高中 VS 永仁高中 1/30 女子复赛(普)"}, {"start": "15:20", "end": "17:00", "title": "LIVE HBL 三重商工 VS 锦和高中 1/30 男子准决赛(普)"}, {"start": "17:00", "end": "18:40", "title": "LIVE HBL 能仁家商 VS 东泰高中 1/30 男子准决赛(普)"}, {"start": "18:40", "end": "21:00", "title": "LIVE HBL 松山高中 VS 光复高中 1/30 男子准决赛(普)"}, {"start": "21:00", "end": "21:30", "title": "NBA动态#12(普)"}, {"start": "21:30", "end": "22:00", "title": "英超名人堂 #33 Eidur Gudjohnsen(普)"}, {"start": "22:00", "end": "22:30", "title": "LIVE 体坛最前线 1/30(普)"}, {"start": "22:30", "end": "22:50", "title": "2024 BWF世界羽球周报 #3 戴资颖 印度站回顾 & 印尼名人赛前瞻(普)"}, {"start": "22:50", "end": "23:50", "title": "欧冠足球志 #16 小组赛回顾(普)"}, {"start": "23:50", "end": "23:59", "title": "LIVE 亚洲杯足球赛 沙乌地 VS 南韩 16强(普)"}, {"start": "02:00", "end": "02:30", "title": "英超名人堂 #33 Eidur Gudjohnsen(普)"}, {"start": "02:30", "end": "03:00", "title": "体坛最前线 1/29(普)"}, {"start": "03:00", "end": "04:30", "title": "HBL 永仁高中 VS 淡水商工 1/28 女子复赛(普)"}, {"start": "04:30", "end": "05:00", "title": "体坛最前线 1/29(普)"}, {"start": "05:00", "end": "06:30", "title": "HBL 金瓯女中 VS 北一女中 1/28 女子复赛(普)"}, {"start": "06:30", "end": "07:00", "title": "体坛最前线 1/29(普)"}, {"start": "07:00", "end": "08:30", "title": "HBL 阳明高中 VS 普门中学 1/28 女子复赛(普)"}, {"start": "08:30", "end": "10:00", "title": "HBL 泰山高中 VS 能仁家商 1/28 男子准决赛(普)"}, {"start": "10:00", "end": "10:30", "title": "体坛最前线 1/29(普)"}, {"start": "10:30", "end": "12:00", "title": "HBL 光复高中 VS 锦和高中 1/28 男子准决赛(普)"}, {"start": "12:00", "end": "13:40", "title": "LIVE HBL 金瓯女中 VS 永平高中 1/30 女子复赛(普)"}, {"start": "13:40", "end": "15:20", "title": "LIVE HBL 阳明高中 VS 永仁高中 1/30 女子复赛(普)"}, {"start": "15:20", "end": "17:00", "title": "LIVE HBL 三重商工 VS 锦和高中 1/30 男子准决赛(普)"}, {"start": "17:00", "end": "18:40", "title": "LIVE HBL 能仁家商 VS 东泰高中 1/30 男子准决赛(普)"}, {"start": "18:40", "end": "21:00", "title": "LIVE HBL 松山高中 VS 光复高中 1/30 男子准决赛(普)"}, {"start": "21:00", "end": "21:30", "title": "NBA动态#12(普)"}, {"start": "21:30", "end": "22:00", "title": "英超名人堂 #33 Eidur Gudjohnsen(普)"}, {"start": "22:00", "end": "22:30", "title": "LIVE 体坛最前线 1/30(普)"}, {"start": "22:30", "end": "22:50", "title": "2024 BWF世界羽球周报 #3 戴资颖 印度站回顾 & 印尼名人赛前瞻(普)"}, {"start": "22:50", "end": "23:50", "title": "欧冠足球志 #16 小组赛回顾(普)"}, {"start": "23:50", "end": "23:59", "title": "LIVE 亚洲杯足球赛 沙乌地 VS 南韩 16强(普)"}, {"start": "02:00", "end": "02:30", "title": "英超名人堂 #33 Eidur Gudjohnsen(普)"}, {"start": "02:30", "end": "03:00", "title": "体坛最前线 1/29(普)"}, {"start": "03:00", "end": "04:30", "title": "HBL 永仁高中 VS 淡水商工 1/28 女子复赛(普)"}, {"start": "04:30", "end": "05:00", "title": "体坛最前线 1/29(普)"}, {"start": "05:00", "end": "06:30", "title": "HBL 金瓯女中 VS 北一女中 1/28 女子复赛(普)"}, {"start": "06:30", "end": "07:00", "title": "体坛最前线 1/29(普)"}, {"start": "07:00", "end": "08:30", "title": "HBL 阳明高中 VS 普门中学 1/28 女子复赛(普)"}, {"start": "08:30", "end": "10:00", "title": "HBL 泰山高中 VS 能仁家商 1/28 男子准决赛(普)"}, {"start": "10:00", "end": "10:30", "title": "体坛最前线 1/29(普)"}, {"start": "10:30", "end": "12:00", "title": "HBL 光复高中 VS 锦和高中 1/28 男子准决赛(普)"}, {"start": "12:00", "end": "13:40", "title": "LIVE HBL 金瓯女中 VS 永平高中 1/30 女子复赛(普)"}, {"start": "13:40", "end": "15:20", "title": "LIVE HBL 阳明高中 VS 永仁高中 1/30 女子复赛(普)"}, {"start": "15:20", "end": "17:00", "title": "LIVE HBL 三重商工 VS 锦和高中 1/30 男子准决赛(普)"}, {"start": "17:00", "end": "18:40", "title": "LIVE HBL 能仁家商 VS 东泰高中 1/30 男子准决赛(普)"}, {"start": "18:40", "end": "21:00", "title": "LIVE HBL 松山高中 VS 光复高中 1/30 男子准决赛(普)"}, {"start": "21:00", "end": "21:30", "title": "NBA动态#12(普)"}, {"start": "21:30", "end": "22:00", "title": "英超名人堂 #33 Eidur Gudjohnsen(普)"}, {"start": "22:00", "end": "22:30", "title": "LIVE 体坛最前线 1/30(普)"}, {"start": "22:30", "end": "22:50", "title": "2024 BWF世界羽球周报 #3 戴资颖 印度站回顾 & 印尼名人赛前瞻(普)"}, {"start": "22:50", "end": "23:50", "title": "欧冠足球志 #16 小组赛回顾(普)"}, {"start": "23:50", "end": "23:59", "title": "LIVE 亚洲杯足球赛 沙乌地 VS 南韩 16强(普)"}, {"start": "02:00", "end": "02:30", "title": "英超名人堂 #33 Eidur Gudjohnsen(普)"}, {"start": "02:30", "end": "03:00", "title": "体坛最前线 1/29(普)"}, {"start": "03:00", "end": "04:30", "title": "HBL 永仁高中 VS 淡水商工 1/28 女子复赛(普)"}, {"start": "04:30", "end": "05:00", "title": "体坛最前线 1/29(普)"}, {"start": "05:00", "end": "06:30", "title": "HBL 金瓯女中 VS 北一女中 1/28 女子复赛(普)"}, {"start": "06:30", "end": "07:00", "title": "体坛最前线 1/29(普)"}, {"start": "07:00", "end": "08:30", "title": "HBL 阳明高中 VS 普门中学 1/28 女子复赛(普)"}, {"start": "08:30", "end": "10:00", "title": "HBL 泰山高中 VS 能仁家商 1/28 男子准决赛(普)"}, {"start": "10:00", "end": "10:30", "title": "体坛最前线 1/29(普)"}, {"start": "10:30", "end": "12:00", "title": "HBL 光复高中 VS 锦和高中 1/28 男子准决赛(普)"}, {"start": "12:00", "end": "13:40", "title": "LIVE HBL 金瓯女中 VS 永平高中 1/30 女子复赛(普)"}, {"start": "13:40", "end": "15:20", "title": "LIVE HBL 阳明高中 VS 永仁高中 1/30 女子复赛(普)"}, {"start": "15:20", "end": "17:00", "title": "LIVE HBL 三重商工 VS 锦和高中 1/30 男子准决赛(普)"}, {"start": "17:00", "end": "18:40", "title": "LIVE HBL 能仁家商 VS 东泰高中 1/30 男子准决赛(普)"}, {"start": "18:40", "end": "21:00", "title": "LIVE HBL 松山高中 VS 光复高中 1/30 男子准决赛(普)"}, {"start": "21:00", "end": "21:30", "title": "NBA动态#12(普)"}, {"start": "21:30", "end": "22:00", "title": "英超名人堂 #33 Eidur Gudjohnsen(普)"}, {"start": "22:00", "end": "22:30", "title": "LIVE 体坛最前线 1/30(普)"}, {"start": "22:30", "end": "22:50", "title": "2024 BWF世界羽球周报 #3 戴资颖 印度站回顾 & 印尼名人赛前瞻(普)"}, {"start": "22:50", "end": "23:50", "title": "欧冠足球志 #16 小组赛回顾(普)"}, {"start": "23:50", "end": "23:59", "title": "LIVE 亚洲杯足球赛 沙乌地 VS 南韩 16强(普)"}, {"start": "02:00", "end": "02:30", "title": "英超名人堂 #33 Eidur Gudjohnsen(普)"}, {"start": "02:30", "end": "03:00", "title": "体坛最前线 1/29(普)"}, {"start": "03:00", "end": "04:30", "title": "HBL 永仁高中 VS 淡水商工 1/28 女子复赛(普)"}, {"start": "04:30", "end": "05:00", "title": "体坛最前线 1/29(普)"}, {"start": "05:00", "end": "06:30", "title": "HBL 金瓯女中 VS 北一女中 1/28 女子复赛(普)"}, {"start": "06:30", "end": "07:00", "title": "体坛最前线 1/29(普)"}, {"start": "07:00", "end": "08:30", "title": "HBL 阳明高中 VS 普门中学 1/28 女子复赛(普)"}, {"start": "08:30", "end": "10:00", "title": "HBL 泰山高中 VS 能仁家商 1/28 男子准决赛(普)"}, {"start": "10:00", "end": "10:30", "title": "体坛最前线 1/29(普)"}, {"start": "10:30", "end": "12:00", "title": "HBL 光复高中 VS 锦和高中 1/28 男子准决赛(普)"}, {"start": "12:00", "end": "13:40", "title": "LIVE HBL 金瓯女中 VS 永平高中 1/30 女子复赛(普)"}, {"start": "13:40", "end": "15:20", "title": "LIVE HBL 阳明高中 VS 永仁高中 1/30 女子复赛(普)"}, {"start": "15:20", "end": "17:00", "title": "LIVE HBL 三重商工 VS 锦和高中 1/30 男子准决赛(普)"}, {"start": "17:00", "end": "18:40", "title": "LIVE HBL 能仁家商 VS 东泰高中 1/30 男子准决赛(普)"}, {"start": "18:40", "end": "21:00", "title": "LIVE HBL 松山高中 VS 光复高中 1/30 男子准决赛(普)"}, {"start": "21:00", "end": "21:30", "title": "NBA动态#12(普)"}, {"start": "21:30", "end": "22:00", "title": "英超名人堂 #33 Eidur Gudjohnsen(普)"}, {"start": "22:00", "end": "22:30", "title": "LIVE 体坛最前线 1/30(普)"}, {"start": "22:30", "end": "22:50", "title": "2024 BWF世界羽球周报 #3 戴资颖 印度站回顾 & 印尼名人赛前瞻(普)"}, {"start": "22:50", "end": "23:50", "title": "欧冠足球志 #16 小组赛回顾(普)"}, {"start": "23:50", "end": "23:59", "title": "LIVE 亚洲杯足球赛 沙乌地 VS 南韩 16强(普)"}]}