{"date": "2024-02-02", "channel_name": "博斯高球2台", "epg_data": [{"start": "04:00", "end": "08:00", "title": "2023 亚巡台玻台丰公开赛 第四回合(普)"}, {"start": "08:00", "end": "12:00", "title": "2023 LPGA日本菁英赛 第四天(普)"}, {"start": "12:00", "end": "15:00", "title": "首播 2024亚太业馀女子锦标赛 第一天(普)"}, {"start": "15:00", "end": "18:00", "title": "LIVE 2024亚太业馀女子锦标赛 第二天(普)"}, {"start": "18:00", "end": "21:30", "title": "2023 亚巡新加坡国际亚巡赛 第一天(普)"}, {"start": "21:30", "end": "23:59", "title": "2023 LPGACME巡回年终锦标赛 第一天(普)"}, {"start": "04:00", "end": "08:00", "title": "2023 亚巡台玻台丰公开赛 第四回合(普)"}, {"start": "08:00", "end": "12:00", "title": "2023 LPGA日本菁英赛 第四天(普)"}, {"start": "12:00", "end": "15:00", "title": "首播 2024亚太业馀女子锦标赛 第一天(普)"}, {"start": "15:00", "end": "18:00", "title": "LIVE 2024亚太业馀女子锦标赛 第二天(普)"}, {"start": "18:00", "end": "21:30", "title": "2023 亚巡新加坡国际亚巡赛 第一天(普)"}, {"start": "21:30", "end": "23:59", "title": "2023 LPGACME巡回年终锦标赛 第一天(普)"}, {"start": "04:00", "end": "08:00", "title": "2023 亚巡台玻台丰公开赛 第四回合(普)"}, {"start": "08:00", "end": "12:00", "title": "2023 LPGA日本菁英赛 第四天(普)"}, {"start": "12:00", "end": "15:00", "title": "首播 2024亚太业馀女子锦标赛 第一天(普)"}, {"start": "15:00", "end": "18:00", "title": "LIVE 2024亚太业馀女子锦标赛 第二天(普)"}, {"start": "18:00", "end": "21:30", "title": "2023 亚巡新加坡国际亚巡赛 第一天(普)"}, {"start": "21:30", "end": "23:59", "title": "2023 LPGACME巡回年终锦标赛 第一天(普)"}, {"start": "04:00", "end": "08:00", "title": "2023 亚巡台玻台丰公开赛 第四回合(普)"}, {"start": "08:00", "end": "12:00", "title": "2023 LPGA日本菁英赛 第四天(普)"}, {"start": "12:00", "end": "15:00", "title": "首播 2024亚太业馀女子锦标赛 第一天(普)"}, {"start": "15:00", "end": "18:00", "title": "LIVE 2024亚太业馀女子锦标赛 第二天(普)"}, {"start": "18:00", "end": "21:30", "title": "2023 亚巡新加坡国际亚巡赛 第一天(普)"}, {"start": "21:30", "end": "23:59", "title": "2023 LPGACME巡回年终锦标赛 第一天(普)"}, {"start": "04:00", "end": "08:00", "title": "2023 亚巡台玻台丰公开赛 第四回合(普)"}, {"start": "08:00", "end": "12:00", "title": "2023 LPGA日本菁英赛 第四天(普)"}, {"start": "12:00", "end": "15:00", "title": "首播 2024亚太业馀女子锦标赛 第一天(普)"}, {"start": "15:00", "end": "18:00", "title": "LIVE 2024亚太业馀女子锦标赛 第二天(普)"}, {"start": "18:00", "end": "21:30", "title": "2023 亚巡新加坡国际亚巡赛 第一天(普)"}, {"start": "21:30", "end": "23:59", "title": "2023 LPGACME巡回年终锦标赛 第一天(普)"}, {"start": "04:00", "end": "08:00", "title": "2023 亚巡台玻台丰公开赛 第四回合(普)"}, {"start": "08:00", "end": "12:00", "title": "2023 LPGA日本菁英赛 第四天(普)"}, {"start": "12:00", "end": "15:00", "title": "首播 2024亚太业馀女子锦标赛 第一天(普)"}, {"start": "15:00", "end": "18:00", "title": "LIVE 2024亚太业馀女子锦标赛 第二天(普)"}, {"start": "18:00", "end": "21:30", "title": "2023 亚巡新加坡国际亚巡赛 第一天(普)"}, {"start": "21:30", "end": "23:59", "title": "2023 LPGACME巡回年终锦标赛 第一天(普)"}, {"start": "04:00", "end": "08:00", "title": "2023 亚巡台玻台丰公开赛 第四回合(普)"}, {"start": "08:00", "end": "12:00", "title": "2023 LPGA日本菁英赛 第四天(普)"}, {"start": "12:00", "end": "15:00", "title": "首播 2024亚太业馀女子锦标赛 第一天(普)"}, {"start": "15:00", "end": "18:00", "title": "LIVE 2024亚太业馀女子锦标赛 第二天(普)"}, {"start": "18:00", "end": "21:30", "title": "2023 亚巡新加坡国际亚巡赛 第一天(普)"}, {"start": "21:30", "end": "23:59", "title": "2023 LPGACME巡回年终锦标赛 第一天(普)"}, {"start": "04:00", "end": "08:00", "title": "2023 亚巡台玻台丰公开赛 第四回合(普)"}, {"start": "08:00", "end": "12:00", "title": "2023 LPGA日本菁英赛 第四天(普)"}, {"start": "12:00", "end": "15:00", "title": "首播 2024亚太业馀女子锦标赛 第一天(普)"}, {"start": "15:00", "end": "18:00", "title": "LIVE 2024亚太业馀女子锦标赛 第二天(普)"}, {"start": "18:00", "end": "21:30", "title": "2023 亚巡新加坡国际亚巡赛 第一天(普)"}, {"start": "21:30", "end": "23:59", "title": "2023 LPGACME巡回年终锦标赛 第一天(普)"}, {"start": "04:00", "end": "08:00", "title": "2023 亚巡台玻台丰公开赛 第四回合(普)"}, {"start": "08:00", "end": "12:00", "title": "2023 LPGA日本菁英赛 第四天(普)"}, {"start": "12:00", "end": "15:00", "title": "首播 2024亚太业馀女子锦标赛 第一天(普)"}, {"start": "15:00", "end": "18:00", "title": "LIVE 2024亚太业馀女子锦标赛 第二天(普)"}, {"start": "18:00", "end": "21:30", "title": "2023 亚巡新加坡国际亚巡赛 第一天(普)"}, {"start": "21:30", "end": "23:59", "title": "2023 LPGACME巡回年终锦标赛 第一天(普)"}, {"start": "04:00", "end": "08:00", "title": "2023 亚巡台玻台丰公开赛 第四回合(普)"}, {"start": "08:00", "end": "12:00", "title": "2023 LPGA日本菁英赛 第四天(普)"}, {"start": "12:00", "end": "15:00", "title": "首播 2024亚太业馀女子锦标赛 第一天(普)"}, {"start": "15:00", "end": "18:00", "title": "LIVE 2024亚太业馀女子锦标赛 第二天(普)"}, {"start": "18:00", "end": "21:30", "title": "2023 亚巡新加坡国际亚巡赛 第一天(普)"}, {"start": "21:30", "end": "23:59", "title": "2023 LPGACME巡回年终锦标赛 第一天(普)"}, {"start": "04:00", "end": "08:00", "title": "2023 亚巡台玻台丰公开赛 第四回合(普)"}, {"start": "08:00", "end": "12:00", "title": "2023 LPGA日本菁英赛 第四天(普)"}, {"start": "12:00", "end": "15:00", "title": "首播 2024亚太业馀女子锦标赛 第一天(普)"}, {"start": "15:00", "end": "18:00", "title": "LIVE 2024亚太业馀女子锦标赛 第二天(普)"}, {"start": "18:00", "end": "21:30", "title": "2023 亚巡新加坡国际亚巡赛 第一天(普)"}, {"start": "21:30", "end": "23:59", "title": "2023 LPGACME巡回年终锦标赛 第一天(普)"}, {"start": "04:00", "end": "08:00", "title": "2023 亚巡台玻台丰公开赛 第四回合(普)"}, {"start": "08:00", "end": "12:00", "title": "2023 LPGA日本菁英赛 第四天(普)"}, {"start": "12:00", "end": "15:00", "title": "首播 2024亚太业馀女子锦标赛 第一天(普)"}, {"start": "15:00", "end": "18:00", "title": "LIVE 2024亚太业馀女子锦标赛 第二天(普)"}, {"start": "18:00", "end": "21:30", "title": "2023 亚巡新加坡国际亚巡赛 第一天(普)"}, {"start": "21:30", "end": "23:59", "title": "2023 LPGACME巡回年终锦标赛 第一天(普)"}, {"start": "04:00", "end": "08:00", "title": "2023 亚巡台玻台丰公开赛 第四回合(普)"}, {"start": "08:00", "end": "12:00", "title": "2023 LPGA日本菁英赛 第四天(普)"}, {"start": "12:00", "end": "15:00", "title": "首播 2024亚太业馀女子锦标赛 第一天(普)"}, {"start": "15:00", "end": "18:00", "title": "LIVE 2024亚太业馀女子锦标赛 第二天(普)"}, {"start": "18:00", "end": "21:30", "title": "2023 亚巡新加坡国际亚巡赛 第一天(普)"}, {"start": "21:30", "end": "23:59", "title": "2023 LPGACME巡回年终锦标赛 第一天(普)"}, {"start": "04:00", "end": "08:00", "title": "2023 亚巡台玻台丰公开赛 第四回合(普)"}, {"start": "08:00", "end": "12:00", "title": "2023 LPGA日本菁英赛 第四天(普)"}, {"start": "12:00", "end": "15:00", "title": "首播 2024亚太业馀女子锦标赛 第一天(普)"}, {"start": "15:00", "end": "18:00", "title": "LIVE 2024亚太业馀女子锦标赛 第二天(普)"}, {"start": "18:00", "end": "21:30", "title": "2023 亚巡新加坡国际亚巡赛 第一天(普)"}, {"start": "21:30", "end": "23:59", "title": "2023 LPGACME巡回年终锦标赛 第一天(普)"}, {"start": "04:00", "end": "08:00", "title": "2023 亚巡台玻台丰公开赛 第四回合(普)"}, {"start": "08:00", "end": "12:00", "title": "2023 LPGA日本菁英赛 第四天(普)"}, {"start": "12:00", "end": "15:00", "title": "首播 2024亚太业馀女子锦标赛 第一天(普)"}, {"start": "15:00", "end": "18:00", "title": "LIVE 2024亚太业馀女子锦标赛 第二天(普)"}, {"start": "18:00", "end": "21:30", "title": "2023 亚巡新加坡国际亚巡赛 第一天(普)"}, {"start": "21:30", "end": "23:59", "title": "2023 LPGACME巡回年终锦标赛 第一天(普)"}, {"start": "04:00", "end": "08:00", "title": "2023 亚巡台玻台丰公开赛 第四回合(普)"}, {"start": "08:00", "end": "12:00", "title": "2023 LPGA日本菁英赛 第四天(普)"}, {"start": "12:00", "end": "15:00", "title": "首播 2024亚太业馀女子锦标赛 第一天(普)"}, {"start": "15:00", "end": "18:00", "title": "LIVE 2024亚太业馀女子锦标赛 第二天(普)"}, {"start": "18:00", "end": "21:30", "title": "2023 亚巡新加坡国际亚巡赛 第一天(普)"}, {"start": "21:30", "end": "23:59", "title": "2023 LPGACME巡回年终锦标赛 第一天(普)"}, {"start": "04:00", "end": "08:00", "title": "2023 亚巡台玻台丰公开赛 第四回合(普)"}, {"start": "08:00", "end": "12:00", "title": "2023 LPGA日本菁英赛 第四天(普)"}, {"start": "12:00", "end": "15:00", "title": "首播 2024亚太业馀女子锦标赛 第一天(普)"}, {"start": "15:00", "end": "18:00", "title": "LIVE 2024亚太业馀女子锦标赛 第二天(普)"}, {"start": "18:00", "end": "21:30", "title": "2023 亚巡新加坡国际亚巡赛 第一天(普)"}, {"start": "21:30", "end": "23:59", "title": "2023 LPGACME巡回年终锦标赛 第一天(普)"}, {"start": "04:00", "end": "08:00", "title": "2023 亚巡台玻台丰公开赛 第四回合(普)"}, {"start": "08:00", "end": "12:00", "title": "2023 LPGA日本菁英赛 第四天(普)"}, {"start": "12:00", "end": "15:00", "title": "首播 2024亚太业馀女子锦标赛 第一天(普)"}, {"start": "15:00", "end": "18:00", "title": "LIVE 2024亚太业馀女子锦标赛 第二天(普)"}, {"start": "18:00", "end": "21:30", "title": "2023 亚巡新加坡国际亚巡赛 第一天(普)"}, {"start": "21:30", "end": "23:59", "title": "2023 LPGACME巡回年终锦标赛 第一天(普)"}]}