{"date": "2024-02-03", "channel_name": "J2", "epg_data": [{"start": "00:05", "end": "00:35", "title": "就是爱美丽[粤/普]-Just Beauty (Sr.4)[Can/Man]"}, {"start": "00:35", "end": "01:05", "title": "北欧潮什么[粤]-Hipster Tour - Scandinavia[Can]"}, {"start": "01:05", "end": "01:35", "title": "还原神之食[粤]-Food Mister[Can]"}, {"start": "01:35", "end": "02:35", "title": "黄金庭院#26[粤/韩]-Golden Garden#26[Can/Kor]"}, {"start": "02:35", "end": "03:05", "title": "网红甜卡[粤]-Pretty Sweet[Can]"}, {"start": "03:05", "end": "03:35", "title": "不如食豪D[粤]-SIK HO D[Can]"}, {"start": "03:35", "end": "04:05", "title": "古灵精怪 台湾篇[粤][PG]-Shocking Asia Reboot: Taiwan[Can][PG]"}, {"start": "04:05", "end": "05:05", "title": "红色高踭鞋#10[粤/韩][PG]-Red Shoes#10[Can/Kor][PG]"}, {"start": "05:05", "end": "05:30", "title": "兄弟帮[粤]-Big Boys Club[Can]"}, {"start": "00:05", "end": "00:35", "title": "就是爱美丽[粤/普]-Just Beauty (Sr.4)[Can/Man]"}, {"start": "00:35", "end": "01:05", "title": "北欧潮什么[粤]-Hipster Tour - Scandinavia[Can]"}, {"start": "01:05", "end": "01:35", "title": "还原神之食[粤]-Food Mister[Can]"}, {"start": "01:35", "end": "02:35", "title": "黄金庭院#26[粤/韩]-Golden Garden#26[Can/Kor]"}, {"start": "02:35", "end": "03:05", "title": "网红甜卡[粤]-Pretty Sweet[Can]"}, {"start": "03:05", "end": "03:35", "title": "不如食豪D[粤]-SIK HO D[Can]"}, {"start": "03:35", "end": "04:05", "title": "古灵精怪 台湾篇[粤][PG]-Shocking Asia Reboot: Taiwan[Can][PG]"}, {"start": "04:05", "end": "05:05", "title": "红色高踭鞋#10[粤/韩][PG]-Red Shoes#10[Can/Kor][PG]"}, {"start": "05:05", "end": "05:30", "title": "兄弟帮[粤]-Big Boys Club[Can]"}, {"start": "00:05", "end": "00:35", "title": "就是爱美丽[粤/普]-Just Beauty (Sr.4)[Can/Man]"}, {"start": "00:35", "end": "01:05", "title": "北欧潮什么[粤]-Hipster Tour - Scandinavia[Can]"}, {"start": "01:05", "end": "01:35", "title": "还原神之食[粤]-Food Mister[Can]"}, {"start": "01:35", "end": "02:35", "title": "黄金庭院#26[粤/韩]-Golden Garden#26[Can/Kor]"}, {"start": "02:35", "end": "03:05", "title": "网红甜卡[粤]-Pretty Sweet[Can]"}, {"start": "03:05", "end": "03:35", "title": "不如食豪D[粤]-SIK HO D[Can]"}, {"start": "03:35", "end": "04:05", "title": "古灵精怪 台湾篇[粤][PG]-Shocking Asia Reboot: Taiwan[Can][PG]"}, {"start": "04:05", "end": "05:05", "title": "红色高踭鞋#10[粤/韩][PG]-Red Shoes#10[Can/Kor][PG]"}, {"start": "05:05", "end": "05:30", "title": "兄弟帮[粤]-Big Boys Club[Can]"}, {"start": "05:30", "end": "06:00", "title": "兄弟帮[粤]-Big Boys Club[Can]"}, {"start": "06:00", "end": "08:00", "title": "断唔断舍离?[粤/日]-DanShaRi: Deny Dispose Detach ~Cleanse Your Home and Mind~~[Can/Jap]"}, {"start": "08:00", "end": "08:30", "title": "北欧潮什么[粤]-Hipster Tour - Scandinavia[Can]"}, {"start": "08:30", "end": "09:00", "title": "出走地图[粤/普]-Off the Grid (Sr.3)[Can/Man]"}, {"start": "09:00", "end": "10:00", "title": "镇乡之宝[粤/普]-Gems of the Lands[Can/Man]"}, {"start": "10:00", "end": "10:30", "title": "兄弟帮[粤]-Big Boys Club[Can]"}, {"start": "10:30", "end": "11:00", "title": "开卷[粤]-Open Book[Can]"}, {"start": "11:00", "end": "11:30", "title": "玲玲友情报[粤]-Ring Ling Ling[Can]"}, {"start": "11:30", "end": "12:00", "title": "古灵精怪 台湾篇[粤][PG]-Shocking Asia Reboot: Taiwan[Can][PG]"}, {"start": "12:00", "end": "13:00", "title": "救参家族#7[粤/日][PG]-My Family#7[Can/Jap][PG]"}, {"start": "13:00", "end": "13:30", "title": "野外步出[粤]-Were All Wildlings[Can]"}, {"start": "13:30", "end": "14:00", "title": "野外步出[粤]-Were All Wildlings[Can]"}, {"start": "14:00", "end": "15:00", "title": "日常生活抢知识[粤/日]-Dounanoka[Can/Jap]"}, {"start": "15:00", "end": "15:30", "title": "无心睡眠[粤]-Before Sunrise[Can]"}, {"start": "15:30", "end": "16:25", "title": "街头少女战士[粤/韩]-Street Dance Girls Fighter[Can/Kor]"}, {"start": "16:25", "end": "16:40", "title": "爱家人物[粤]-Own Sweet Home[Can]"}, {"start": "16:40", "end": "18:40", "title": "断唔断舍离?[粤/日]-DanShaRi: Deny Dispose Detach ~Cleanse Your Home and Mind~~[Can/Jap]"}, {"start": "18:40", "end": "20:30", "title": "RUNNING MAN[韩]-Running Man (XIX)[Kor]"}, {"start": "20:30", "end": "21:30", "title": "梦想改造家[粤]-Dream Home (V)[Can]"}, {"start": "21:30", "end": "22:30", "title": "镇乡之宝[粤/普]-Gems of the Lands[Can/Man]"}, {"start": "22:30", "end": "23:30", "title": "日本绝恐映像[粤/日][PG]-Tokyo Horror 2021[Can/Jap][PG]"}, {"start": "06:00", "end": "08:00", "title": "断唔断舍离?[粤/日]-DanShaRi: Deny Dispose Detach ~Cleanse Your Home and Mind~~[Can/Jap]"}, {"start": "08:00", "end": "08:30", "title": "北欧潮什么[粤]-Hipster Tour - Scandinavia[Can]"}, {"start": "08:30", "end": "09:00", "title": "出走地图[粤/普]-Off the Grid (Sr.3)[Can/Man]"}, {"start": "09:00", "end": "10:00", "title": "镇乡之宝[粤/普]-Gems of the Lands[Can/Man]"}, {"start": "10:00", "end": "10:30", "title": "兄弟帮[粤]-Big Boys Club[Can]"}, {"start": "10:30", "end": "11:00", "title": "开卷[粤]-Open Book[Can]"}, {"start": "11:00", "end": "11:30", "title": "玲玲友情报[粤]-Ring Ling Ling[Can]"}, {"start": "11:30", "end": "12:00", "title": "古灵精怪 台湾篇[粤][PG]-Shocking Asia Reboot: Taiwan[Can][PG]"}, {"start": "12:00", "end": "13:00", "title": "救参家族#7[粤/日][PG]-My Family#7[Can/Jap][PG]"}, {"start": "13:00", "end": "13:30", "title": "野外步出[粤]-Were All Wildlings[Can]"}, {"start": "13:30", "end": "14:00", "title": "野外步出[粤]-Were All Wildlings[Can]"}, {"start": "14:00", "end": "15:00", "title": "日常生活抢知识[粤/日]-Dounanoka[Can/Jap]"}, {"start": "15:00", "end": "15:30", "title": "无心睡眠[粤]-Before Sunrise[Can]"}, {"start": "15:30", "end": "16:25", "title": "街头少女战士[粤/韩]-Street Dance Girls Fighter[Can/Kor]"}, {"start": "16:25", "end": "16:40", "title": "爱家人物[粤]-Own Sweet Home[Can]"}, {"start": "16:40", "end": "18:40", "title": "断唔断舍离?[粤/日]-DanShaRi: Deny Dispose Detach ~Cleanse Your Home and Mind~~[Can/Jap]"}, {"start": "18:40", "end": "20:30", "title": "RUNNING MAN[韩]-Running Man (XIX)[Kor]"}, {"start": "20:30", "end": "21:30", "title": "梦想改造家[粤]-Dream Home (V)[Can]"}, {"start": "21:30", "end": "22:30", "title": "镇乡之宝[粤/普]-Gems of the Lands[Can/Man]"}, {"start": "22:30", "end": "23:30", "title": "日本绝恐映像[粤/日][PG]-Tokyo Horror 2021[Can/Jap][PG]"}, {"start": "06:00", "end": "08:00", "title": "断唔断舍离?[粤/日]-DanShaRi: Deny Dispose Detach ~Cleanse Your Home and Mind~~[Can/Jap]"}, {"start": "08:00", "end": "08:30", "title": "北欧潮什么[粤]-Hipster Tour - Scandinavia[Can]"}, {"start": "08:30", "end": "09:00", "title": "出走地图[粤/普]-Off the Grid (Sr.3)[Can/Man]"}, {"start": "09:00", "end": "10:00", "title": "镇乡之宝[粤/普]-Gems of the Lands[Can/Man]"}, {"start": "10:00", "end": "10:30", "title": "兄弟帮[粤]-Big Boys Club[Can]"}, {"start": "10:30", "end": "11:00", "title": "开卷[粤]-Open Book[Can]"}, {"start": "11:00", "end": "11:30", "title": "玲玲友情报[粤]-Ring Ling Ling[Can]"}, {"start": "11:30", "end": "12:00", "title": "古灵精怪 台湾篇[粤][PG]-Shocking Asia Reboot: Taiwan[Can][PG]"}, {"start": "12:00", "end": "13:00", "title": "救参家族#7[粤/日][PG]-My Family#7[Can/Jap][PG]"}, {"start": "13:00", "end": "13:30", "title": "野外步出[粤]-Were All Wildlings[Can]"}, {"start": "13:30", "end": "14:00", "title": "野外步出[粤]-Were All Wildlings[Can]"}, {"start": "14:00", "end": "15:00", "title": "日常生活抢知识[粤/日]-Dounanoka[Can/Jap]"}, {"start": "15:00", "end": "15:30", "title": "无心睡眠[粤]-Before Sunrise[Can]"}, {"start": "15:30", "end": "16:25", "title": "街头少女战士[粤/韩]-Street Dance Girls Fighter[Can/Kor]"}, {"start": "16:25", "end": "16:40", "title": "爱家人物[粤]-Own Sweet Home[Can]"}, {"start": "16:40", "end": "18:40", "title": "断唔断舍离?[粤/日]-DanShaRi: Deny Dispose Detach ~Cleanse Your Home and Mind~~[Can/Jap]"}, {"start": "18:40", "end": "20:30", "title": "RUNNING MAN[韩]-Running Man (XIX)[Kor]"}, {"start": "20:30", "end": "21:30", "title": "梦想改造家[粤]-Dream Home (V)[Can]"}, {"start": "21:30", "end": "22:30", "title": "镇乡之宝[粤/普]-Gems of the Lands[Can/Man]"}, {"start": "22:30", "end": "23:30", "title": "日本绝恐映像[粤/日][PG]-Tokyo Horror 2021[Can/Jap][PG]"}]}