{"date": "2024-02-03", "channel_name": "揭阳综合", "epg_data": [{"start": "00:30", "end": "07:50", "title": "休台"}, {"start": "07:50", "end": "08:00", "title": "故宫100"}, {"start": "08:00", "end": "08:03", "title": "中华人民共和国国歌"}, {"start": "08:03", "end": "08:50", "title": "亲爱的孩子们(24)"}, {"start": "08:50", "end": "09:50", "title": "亲爱的孩子们(25)"}, {"start": "09:50", "end": "10:35", "title": "爱的厘米(13)"}, {"start": "10:35", "end": "11:20", "title": "爱的厘米(14)"}, {"start": "11:20", "end": "12:00", "title": "爱的厘米(15)"}, {"start": "12:00", "end": "12:30", "title": "揭阳新闻"}, {"start": "12:30", "end": "13:20", "title": "民生热线"}, {"start": "13:20", "end": "14:10", "title": "绝密使命(11)"}, {"start": "14:10", "end": "15:00", "title": "绝密使命(12)"}, {"start": "15:00", "end": "15:50", "title": "绝密使命(13)"}, {"start": "15:50", "end": "16:40", "title": "绝密使命(14)"}, {"start": "16:40", "end": "17:15", "title": "绝密使命(15)"}, {"start": "17:15", "end": "18:00", "title": "绝密使命(16)"}, {"start": "18:00", "end": "18:10", "title": "虹猫蓝兔梦之国历险记(39)"}, {"start": "18:10", "end": "18:30", "title": "虹猫蓝兔梦之国历险记(40)"}, {"start": "18:30", "end": "19:00", "title": "广东新闻联播"}, {"start": "19:00", "end": "19:40", "title": "转播中央台新闻联播"}, {"start": "19:40", "end": "20:01", "title": "揭阳新闻"}, {"start": "20:01", "end": "20:20", "title": "县区之窗"}, {"start": "20:20", "end": "20:30", "title": "发现揭东(84)"}, {"start": "20:30", "end": "21:30", "title": "亲爱的孩子们(26)"}, {"start": "21:30", "end": "22:00", "title": "民生热线"}, {"start": "22:00", "end": "22:50", "title": "亲爱的孩子们(27)"}, {"start": "22:50", "end": "23:00", "title": "了不起的匠人"}, {"start": "23:00", "end": "23:30", "title": "揭阳新闻"}, {"start": "23:30", "end": "23:59", "title": "闭台曲"}]}